lightcurves/__init__.py
lightcurves/_version.py
lightcurves/hop.py
lightcurves/hop_finder.py
lightcurves/lc.py
lightcurves/lc_set.py
lightcurves/version.py
lightcurves-1.1.1.dist-info/METADATA
lightcurves-1.1.1.dist-info/WHEEL
lightcurves-1.1.1.dist-info/licenses/LICENSE.txt
lightcurves-1.1.1.dist-info/RECORD
