Metadata-Version: 2.4
Name: lightcurves
Version: 1.1.1
Summary: A package to analyze any kind of light curve/time series, e.g. with Bayesian Blocks, flare fitting (HOP), and a stochastic processe
Author-email: Sarah Wagner <sarahwagner1602@gmail.com>
Maintainer-email: Sarah Wagner <sarahwagner1602@gmail.com>
License: MIT
License-File: LICENSE.txt
Classifier: Development Status :: 4 - Beta
Classifier: Intended Audience :: Science/Research
Classifier: License :: OSI Approved :: MIT License
Classifier: Programming Language :: Python :: 3
Classifier: Programming Language :: Python :: 3.10
Classifier: Programming Language :: Python :: 3.11
Classifier: Topic :: Scientific/Engineering :: Astronomy
Classifier: Topic :: Scientific/Engineering :: Physics
Requires-Python: >=3.10
Requires-Dist: astropy
Requires-Dist: lmfit
Requires-Dist: matplotlib
Requires-Dist: numpy
Requires-Dist: pandas
Requires-Dist: scipy
Requires-Dist: tqdm
Provides-Extra: test
Requires-Dist: pytest; extra == 'test'
